pyWrite/__init__.py
pyWrite/pyJson.py
pyWrite/pyWrite.py
pyWrites-0.0.6.dist-info/LICENSE.txt
pyWrites-0.0.6.dist-info/METADATA
pyWrites-0.0.6.dist-info/WHEEL
pyWrites-0.0.6.dist-info/top_level.txt
pyWrites-0.0.6.dist-info/RECORD
