Metadata-Version: 2.1
Name: pyWrites
Version: 0.0.6
Summary: pyWrites to files package!
Author: Beere
Author-email: <timoschneiderr@outlook.de>
Keywords: python,write,File,pyWrites,read,delete
Classifier: Development Status :: 3 - Alpha
Classifier: Intended Audience :: Developers
Classifier: Programming Language :: Python :: 3
Classifier: Operating System :: Unix
Classifier: Operating System :: MacOS :: MacOS X
Classifier: Operating System :: Microsoft :: Windows
License-File: LICENSE.txt
Requires-Dist: cryptography
